setup.cfg
setup.py
kevy_stats_pac/Binomialdistribution.py
kevy_stats_pac/Gaussiandistribution.py
kevy_stats_pac/Generaldistribution.py
kevy_stats_pac/__init__.py
kevy_stats_pac.egg-info/PKG-INFO
kevy_stats_pac.egg-info/SOURCES.txt
kevy_stats_pac.egg-info/dependency_links.txt
kevy_stats_pac.egg-info/not-zip-safe
kevy_stats_pac.egg-info/top_level.txt