Metadata-Version: 1.0
Name: kevy-stats-pac
Version: 0.0
Summary: Calculate and visuallize, Gaussian, Binomial and Normal distributions
Home-page: UNKNOWN
Author: UNKNOWN
Author-email: mpofukelvintafadzwa@gmail.com
License: UNKNOWN
Platform: UNKNOWN
